evaluatorq/__init__.py
evaluatorq/evaluatorq.py
evaluatorq/fetch_data.py
evaluatorq/job_helper.py
evaluatorq/processings.py
evaluatorq/progress.py
evaluatorq/py.typed
evaluatorq/send_results.py
evaluatorq/table_display.py
evaluatorq/types.py
evaluatorq-1.0.2.dist-info/METADATA
evaluatorq-1.0.2.dist-info/WHEEL
evaluatorq-1.0.2.dist-info/RECORD
