Metadata-Version: 2.4
Name: evaluatorq
Version: 1.0.2
Summary: An evaluation framework library for Python that provides a flexible way to run parallel evaluations and optionally integrate with the Orq AI platform.
Project-URL: Homepage, https://github.com/orq-ai/orqkit
Project-URL: Repository, https://github.com/orq-ai/orqkit/tree/main/packages/evaluatorq-py
Project-URL: Documentation, https://github.com/orq-ai/orqkit/tree/main/packages/evaluatorq-py
License: MIT
Requires-Python: >=3.10
Requires-Dist: httpx>=0.28.1
Requires-Dist: pydantic>=2.0
Requires-Dist: rich>=14.2.0
Provides-Extra: orq
Requires-Dist: orq-ai-sdk>=3.13.16; extra == 'orq'
